cs2tc/__init__.py
cs2tc-0.1.1.dist-info/LICENSE
cs2tc-0.1.1.dist-info/METADATA
cs2tc-0.1.1.dist-info/WHEEL
cs2tc-0.1.1.dist-info/top_level.txt
cs2tc-0.1.1.dist-info/RECORD
