Metadata-Version: 2.1
Name: cs2tc
Version: 0.1.1
Summary: Helper functions for converting Compute Studio parameters to a format compatible with Tax-Calculator.
Home-page: https://github.com/hdoupe/cs2tc
Author: Hank Doupe
Author-email: henrymdoupe@gmail.com
License: UNKNOWN
Platform: UNKNOWN
Classifier: Programming Language :: Python :: 3
Classifier: License :: OSI Approved :: MIT License
Classifier: Operating System :: OS Independent
Requires-Dist: paramtools
